ThInfluxSDK/__init__.py
ThInfluxSDK/influxSDK.py
th_influx_sdk-1.3.7.dist-info/METADATA
th_influx_sdk-1.3.7.dist-info/WHEEL
th_influx_sdk-1.3.7.dist-info/top_level.txt
th_influx_sdk-1.3.7.dist-info/RECORD
