Metadata-Version: 2.1
Name: th-influx-sdk
Version: 1.3.7
Summary: A SDK for influxDb
Author: xiongyi
Author-email: 15679191752@163.com
Requires-Dist: influxdb ==5.3.2
Requires-Dist: python-dateutil >=2.9.0.post0
